remote_llm/__init__.py
remote_llm/base_llm.py
remote_llm/client.py
remote_llm/gpt_neo_wrap.py
remote_llm/keystore.py
remote_llm/langchain_wrap.py
remote_llm/schema.py
remote_llm/server.py
remote_llm/llm_rpc/__init__.py
remote_llm/llm_rpc/api.py
remote_llm-0.0.1.dist-info/METADATA
remote_llm-0.0.1.dist-info/WHEEL
remote_llm-0.0.1.dist-info/top_level.txt
remote_llm-0.0.1.dist-info/RECORD
